cowgol_compat/arch.coh
cowgol_compat/archlink.coh
cowgol_compat/cobin.coh
cowgol_compat/cobout.coh
cowgol_compat/inssel.coh
cowgol_compat/inssel.decl.coh
cowgol_compat/midcodesbe.coh
cowgol_compat/midcodesfe.coh
cowgol_compat/parser.coh
cowgol_compat/parser.tokens.coh
lib/runtime.mac
src/__init__.py
src/ast.py
src/callgraph.py
src/codegen.py
src/lexer.py
src/main.py
src/optimizer.py
src/parser.py
src/postopt.py
src/preprocessor.py
src/tokens.py
src/types.py
ucow-0.3.0.dist-info/METADATA
ucow-0.3.0.dist-info/WHEEL
ucow-0.3.0.dist-info/entry_points.txt
ucow-0.3.0.dist-info/licenses/LICENSE
ucow-0.3.0.dist-info/RECORD
